LICENSE
MANIFEST.in
README.rst
setup.py
bin/flask-go.py
flask_go/__init__.py
flask_go/management.py
flask_go.egg-info/PKG-INFO
flask_go.egg-info/SOURCES.txt
flask_go.egg-info/dependency_links.txt
flask_go.egg-info/entry_points.txt
flask_go.egg-info/not-zip-safe
flask_go.egg-info/requires.txt
flask_go.egg-info/top_level.txt
flask_go/app_template/__init__.py
flask_go/app_template/views.py
flask_go/commands/__init__.py
flask_go/commands/base.py
flask_go/commands/startapp.py
flask_go/commands/startproject.py
flask_go/project_template/manage.py
flask_go/project_template/requirements.txt
flask_go/project_template/project_name/__init__.py
flask_go/project_template/project_name/project_name.py
flask_go/project_template/project_name/settings.py
flask_go/project_template/project_name/apps/__init__.py
flask_go/project_template/project_name/configs/__init__.py
flask_go/project_template/project_name/configs/base.py