Metadata-Version: 1.1
Name: flask-go
Version: 0.1.1
Summary: Let you create flask project like use django-admin
Home-page: https://github.com/CelloCello/flask-go
Author: Cello Hsueh
Author-email: cello1124@gmail.com
License: BSD
Platform: UNKNOWN
Classifier: Development Status :: 4 - Beta
Classifier: Environment :: Web Environment
Classifier: Intended Audience :: Developers
Classifier: License :: OSI Approved :: BSD License
Classifier: Operating System :: OS Independent
Classifier: Programming Language :: Python
Classifier: Topic :: Internet :: WWW/HTTP :: Dynamic Content
Classifier: Topic :: Software Development :: Libraries :: Python Modules
